modelset/__init__.py
modelset/dataset.py
modelset/deduplication.py
modelset/downloader.py
modelset/word2vec.py
modelset_py-0.2.1.dist-info/LICENSE.md
modelset_py-0.2.1.dist-info/METADATA
modelset_py-0.2.1.dist-info/WHEEL
modelset_py-0.2.1.dist-info/top_level.txt
modelset_py-0.2.1.dist-info/RECORD
