Metadata-Version: 2.1
Name: modelset-py
Version: 0.2.1
Summary: A libray to handle the ModelSet dataset of software models
Home-page: https://github.com/modelset/modelset-py
Author: Jesús Sánchez Cuadrado
Author-email: jesusc@um.es
License: UNKNOWN
Project-URL: Bug Tracker, https://github.com/modelset/modelset-py/issues
Platform: UNKNOWN
Classifier: Programming Language :: Python :: 3
Classifier: License :: OSI Approved :: MIT License
Classifier: Operating System :: OS Independent
Requires-Python: >=3.0
License-File: LICENSE.md
Requires-Dist: gensim (==4.2.0)
Requires-Dist: networkx
Requires-Dist: numpy
Requires-Dist: pandas
Requires-Dist: scikit-learn
Requires-Dist: tqdm
Requires-Dist: wget
